ibm_continuous_delivery/__init__.py
ibm_continuous_delivery/cd_tekton_pipeline_v2.py
ibm_continuous_delivery/cd_toolchain_v2.py
ibm_continuous_delivery/common.py
ibm_continuous_delivery/version.py
ibm_continuous_delivery-2.0.5.dist-info/licenses/LICENSE
ibm_continuous_delivery-2.0.5.dist-info/METADATA
ibm_continuous_delivery-2.0.5.dist-info/WHEEL
ibm_continuous_delivery-2.0.5.dist-info/top_level.txt
ibm_continuous_delivery-2.0.5.dist-info/RECORD
