Metadata-Version: 2.4
Name: ibm_continuous_delivery
Version: 2.0.5
Summary: Python client library to interact with the IBM Cloud Continuous Delivery Toolchain and Tekton Pipeline APIs
Author-email: Omar Al Bastami <omar.albastami@ibm.com>, Brian Gleeson <brian.gleeson@ie.ibm.com>
Project-URL: Repository, https://github.com/IBM/continuous-delivery-python-sdk
Project-URL: Documentation, https://github.com/IBM/continuous-delivery-python-sdk/blob/main/README.md
Project-URL: Issues, https://github.com/IBM/continuous-delivery-python-sdk/issues
Project-URL: Changelog, https://github.com/IBM/continuous-delivery-python-sdk/blob/main/CHANGELOG.md
Project-URL: Contributing, https://github.com/IBM/continuous-delivery-python-sdk/blob/main/CONTRIBUTING.md
Project-URL: License, https://github.com/IBM/continuous-delivery-python-sdk/blob/main/LICENSE
Keywords: ibm,cloud,ibm cloud services,toolchain,tekton
Classifier: Programming Language :: Python
Classifier: Programming Language :: Python :: 3
Classifier: Programming Language :: Python :: 3.9
Classifier: Programming Language :: Python :: 3.10
Classifier: Programming Language :: Python :: 3.11
Classifier: Programming Language :: Python :: 3.12
Classifier: Programming Language :: Python :: 3.13
Classifier: Development Status :: 4 - Beta
Classifier: Environment :: Console
Classifier: Intended Audience :: Developers
Classifier: License :: OSI Approved :: Apache Software License
Classifier: Operating System :: OS Independent
Classifier: Topic :: Software Development :: Libraries
Classifier: Topic :: Software Development :: Libraries :: Python Modules
Classifier: Topic :: Software Development :: Libraries :: Application Frameworks
Requires-Python: >=3.9
License-File: LICENSE
Requires-Dist: ibm_cloud_sdk_core<4.0.0,>=3.24.2
Provides-Extra: dev
Requires-Dist: coverage<8.0.0,>=7.9.0; extra == "dev"
Requires-Dist: pylint<4.0.0,>=3.3.7; extra == "dev"
Requires-Dist: pytest<8.0.0,>=7.4.4; extra == "dev"
Requires-Dist: pytest-cov<5.0.0,>=4.1.0; extra == "dev"
Requires-Dist: responses<1.0.0,>=0.25.7; extra == "dev"
Requires-Dist: black<26.0.0,>=25.0.0; extra == "dev"
Provides-Extra: publish
Requires-Dist: build; extra == "publish"
Requires-Dist: twine; extra == "publish"
Dynamic: license-file
